bccmaths/__init__.py
dictplus/__init__.py
listplus/__init__.py
progressplus/__init__.py
progressplus/progress_bar.py
progressplus/rust_progressbar.pyd
strmaths/__init__.py
strmaths/basicSM.py
strplus/__init__.py
pyafplus-1.1.7.dist-info/METADATA
pyafplus-1.1.7.dist-info/WHEEL
pyafplus-1.1.7.dist-info/top_level.txt
pyafplus-1.1.7.dist-info/RECORD
