Metadata-Version: 2.1
Name: pyafplus
Version: 1.1.7
Summary: Python Advanced Features Plus - 提供多种实用的 Python 扩展功能
Home-page: https://github.com/dhjs0000/PyPlus
Author: dhjs0000
Author-email: dhjsllll@foxmail.com
Keywords: python,utility,progress bar,rust extension,high performance,string math,big number,data structures
Classifier: Development Status :: 5 - Production/Stable
Classifier: Intended Audience :: Developers
Classifier: License :: OSI Approved :: MIT License
Classifier: Operating System :: OS Independent
Classifier: Programming Language :: Python :: 3
Classifier: Programming Language :: Python :: 3.6
Classifier: Programming Language :: Python :: 3.7
Classifier: Programming Language :: Python :: 3.8
Classifier: Programming Language :: Python :: 3.9
Classifier: Programming Language :: Python :: 3.10
Classifier: Programming Language :: Python :: 3.11
Classifier: Programming Language :: Rust
Classifier: Topic :: Software Development :: Libraries :: Python Modules
Requires-Python: >=3.6
